README.md
setup.py
digitapik_photoassist/__init__.py
digitapik_photoassist.egg-info/PKG-INFO
digitapik_photoassist.egg-info/SOURCES.txt
digitapik_photoassist.egg-info/dependency_links.txt
digitapik_photoassist.egg-info/top_level.txt